{
  "task_id": "TASK-011",
  "title": "Recurring QIF spec alignment audit",
  "description": "Run QIF quality-intent/risk/loss audits against docs/specs/v0.1 at each stage boundary and before closing major tasks; update the QIF report, STATUS handoff, and task triage notes with pass/defer/fix decisions.",
  "status": "open",
  "origin": "human",
  "orchestrator_session_id": null,
  "assigned_session_ids": [],
  "related_decision_record_id": null,
  "operating_goal_ref": ".aof/goals/operating-goal.json",
  "created_at": "2026-06-26T19:09:52.981Z",
  "updated_at": "2026-06-26T19:16:28.854Z",
  "assigned_at": null,
  "done_at": null,
  "retired_at": null,
  "last_triaged_at": null,
  "stale_candidate_at": null,
  "retire_candidate_at": null,
  "triage_notes": "QIF cadence applied after TASK-005 public API/render changes: docs/aof/QIF-SPEC-CHECK-2026-06-27.md updated with external src, src_fetch_failed, and diagnostics target/panel progress. Keep open; run again before closing TASK-005 and at each TASK-006+ closure."
}
